{
  "meta": {
    "case_label": "case_08_systemic_gpa",
    "generated_at": "2026-02-22T03:05:04.534871Z",
    "model": "Aura Hierarchical Dual-Scorer v1.0",
    "disclaimer": "This output is generated by an AI clinical decision support tool. It is not a diagnosis. All findings must be reviewed and validated by a qualified physician."
  },
  "patient": {
    "patient_id": "immport_sdy91_114872",
    "age": 55,
    "sex": "M",
    "bmi": null,
    "source_dataset": "immport_sdy91",
    "true_diagnosis_cluster": "systemic",
    "true_diagnosis_raw": "Granulomatosis With Polyangiitis (GPA)",
    "true_diagnosis_icd10": "M31.3"
  },
  "prediction": {
    "predicted_category": "systemic",
    "category_confidence": 0.9569,
    "category_probabilities": {
      "healthy": 0.0381,
      "systemic": 0.9569,
      "gastrointestinal": 0.0019,
      "endocrine": 0.003
    },
    "category_ranking": [
      {
        "category": "systemic",
        "probability": 0.9569
      },
      {
        "category": "healthy",
        "probability": 0.0381
      },
      {
        "category": "endocrine",
        "probability": 0.003
      },
      {
        "category": "gastrointestinal",
        "probability": 0.0019
      }
    ],
    "predicted_disease": "Granulomatosis With Polyangiitis (GPA)",
    "disease_confidence": 0.9992,
    "disease_probabilities": {
      "Ankylosing Spondylitis": 0.0,
      "Granulomatosis With Polyangiitis (GPA)": 0.9992,
      "Normal": 0.0,
      "Psoriatic Arthritis": 0.0,
      "Reactive Arthritis": 0.0,
      "Rheumatoid Arthritis": 0.0001,
      "Scleroderma (Systemic Sclerosis)": 0.0,
      "Sjogren Syndrome": 0.0,
      "Sj\u00f6gren's Syndrome": 0.0,
      "Systemic Lupus Erythematosus": 0.0002,
      "lupus": 0.0,
      "population_survey": 0.0003,
      "psoriatic_arthritis": 0.0,
      "rheumatoid_arthritis": 0.0
    }
  },
  "correct": true,
  "clinical_interpretation": {
    "summary": "Systemic autoimmune pattern detected (96% confidence). Findings are consistent with systemic inflammation \u2014 consider evaluation for lupus, rheumatoid arthritis, Sj\u00f6gren's syndrome, or related conditions.",
    "patient_friendly": "Your results suggest patterns seen in conditions like lupus or rheumatoid arthritis. These are treatable \u2014 early evaluation matters.",
    "recommended_action": "Referral to Rheumatology. Consider: ANA panel, anti-dsDNA, RF, anti-CCP, complement levels (C3/C4), joint X-rays.",
    "confidence_tier": "High (>80%)"
  },
  "lab_panel": {
    "wbc": {
      "value": 5.55,
      "unit": "\u00d710\u00b3/\u00b5L",
      "reference_low": 4.5,
      "reference_high": 11.0,
      "flag": "N",
      "zscore": null,
      "was_ordered": true
    },
    "rbc": {
      "value": null,
      "unit": "\u00d710\u2076/\u00b5L",
      "reference_low": 4.2,
      "reference_high": 5.4,
      "flag": "MISSING",
      "zscore": null,
      "was_ordered": false
    },
    "hemoglobin": {
      "value": 12.5,
      "unit": "g/dL",
      "reference_low": 12.0,
      "reference_high": 17.5,
      "flag": "N",
      "zscore": null,
      "was_ordered": true
    },
    "hematocrit": {
      "value": 36.0,
      "unit": "%",
      "reference_low": 37.0,
      "reference_high": 52.0,
      "flag": "L",
      "zscore": null,
      "was_ordered": true
    },
    "platelet_count": {
      "value": 242.9,
      "unit": "\u00d710\u00b3/\u00b5L",
      "reference_low": 150,
      "reference_high": 400,
      "flag": "N",
      "zscore": null,
      "was_ordered": true
    },
    "mcv": {
      "value": null,
      "unit": "fL",
      "reference_low": 80.0,
      "reference_high": 100.0,
      "flag": "MISSING",
      "zscore": null,
      "was_ordered": false
    },
    "mch": {
      "value": null,
      "unit": "pg",
      "reference_low": 27.0,
      "reference_high": 33.0,
      "flag": "MISSING",
      "zscore": null,
      "was_ordered": false
    },
    "rdw": {
      "value": null,
      "unit": "%",
      "reference_low": 11.5,
      "reference_high": 14.5,
      "flag": "MISSING",
      "zscore": null,
      "was_ordered": false
    },
    "esr": {
      "value": 13.0,
      "unit": "mm/hr",
      "reference_low": 0.0,
      "reference_high": 20.0,
      "flag": "N",
      "zscore": null,
      "was_ordered": true
    },
    "crp": {
      "value": 0.37,
      "unit": "mg/dL",
      "reference_low": 0.0,
      "reference_high": 1.0,
      "flag": "N",
      "zscore": null,
      "was_ordered": true
    }
  },
  "autoantibody_panel": null
}